eventstudystatistics/__init__.py
eventstudystatistics/statistical_tests.py
eventstudystatistics-1.0.0.dist-info/LICENSE.txt
eventstudystatistics-1.0.0.dist-info/METADATA
eventstudystatistics-1.0.0.dist-info/WHEEL
eventstudystatistics-1.0.0.dist-info/top_level.txt
eventstudystatistics-1.0.0.dist-info/RECORD
